CHANGELOG.txt
LICENSE.txt
MANIFEST.in
README.txt
setup.py
test.py
timetils/__init__.py
timetils/classes.py
timetils/formatter.py
timetils/utility.py
timetils.egg-info/PKG-INFO
timetils.egg-info/SOURCES.txt
timetils.egg-info/dependency_links.txt
timetils.egg-info/top_level.txt
timetils/utils/__init__.py
timetils/utils/gets.py